<?xml version="1.0" encoding="utf-8"?><Episode><id>314312</id><Combined_episodenumber>4</Combined_episodenumber><Combined_season>6</Combined_season><DVD_chapter>0</DVD_chapter><DVD_discid></DVD_discid><DVD_episodenumber>4</DVD_episodenumber><DVD_season>6</DVD_season><Director>|John Putch|</Director><EpImgFlag></EpImgFlag><EpisodeName>My House</EpisodeName><EpisodeNumber>4</EpisodeNumber><FirstAired>2007-01-04</FirstAired><GuestStars>|Adrian N. Roberts|Danielle Weeks|Kevin E. West|</GuestStars><IMDB_ID>tt0922244</IMDB_ID><Language>en</Language><Overview>Dr. Cox feels like the TV character House when he has to solve several mysteries, one of them being Elliot's anger towards Dr. Kelso, while for some reason she is taking it out on Turk.
J.D. tries to be a better boyfriend to Kim.</Overview><ProductionCode>604</ProductionCode><Rating>7.4</Rating><RatingCount>1284</RatingCount><SeasonNumber>6</SeasonNumber><Writer>|Bill Callahan|</Writer><absolute_number>121</absolute_number><airsafter_season>0</airsafter_season><airsbefore_episode>0</airsbefore_episode><airsbefore_season>0</airsbefore_season><filename>episodes/76156/314312.jpg</filename><lastupdated>1573649182</lastupdated><seasonid>16440</seasonid><seriesid>76156</seriesid><thumb_added>2019-11-13 12:46:22</thumb_added><thumb_height>480</thumb_height><thumb_width>640</thumb_width></Episode>