<?xml version="1.0" encoding="utf-8"?><Episode><id>443926</id><Combined_episodenumber>14</Combined_episodenumber><Combined_season>7</Combined_season><DVD_chapter>0</DVD_chapter><DVD_discid></DVD_discid><DVD_episodenumber>14</DVD_episodenumber><DVD_season>7</DVD_season><Director>|John Holmquist|</Director><EpImgFlag></EpImgFlag><EpisodeName>We Love You, Conrad</EpisodeName><EpisodeNumber>14</EpisodeNumber><FirstAired>2009-05-03</FirstAired><GuestStars>|Audrina Patridge|Craig Ferguson|Drew Barrymore|Jay Leno|Jimmy Fallon|Lauren Conrad|</GuestStars><IMDB_ID>tt1412043</IMDB_ID><Language>en</Language><Overview>Brian is devastated to learn that his ex-girlfriend Jillian is getting married until he meets The Hills star Lauren Conrad. Though Brian begins to think he and Conrad are the perfect match, he finds his heart may still belong to Jillian.</Overview><ProductionCode>6ACX19</ProductionCode><Rating>7.4</Rating><RatingCount>1437</RatingCount><SeasonNumber>7</SeasonNumber><Writer>|Cherry Chevapravatdumrong|</Writer><absolute_number>124</absolute_number><airsafter_season>0</airsafter_season><airsbefore_episode>0</airsbefore_episode><airsbefore_season>0</airsbefore_season><filename>episodes/75978/443926.jpg</filename><lastupdated>1629554977</lastupdated><seasonid>32348</seasonid><seriesid>75978</seriesid><thumb_added>2019-11-13 11:21:01</thumb_added><thumb_height>480</thumb_height><thumb_width>640</thumb_width></Episode>