<?xml version="1.0" encoding="utf-8"?><Episode><id>306264</id><Combined_episodenumber>24</Combined_episodenumber><Combined_season>4</Combined_season><DVD_chapter>0</DVD_chapter><DVD_discid></DVD_discid><DVD_episodenumber>24</DVD_episodenumber><DVD_season>4</DVD_season><Director>|Kurt Dumas|</Director><EpImgFlag></EpImgFlag><EpisodeName>Peterotica</EpisodeName><EpisodeNumber>24</EpisodeNumber><FirstAired>2006-04-23</FirstAired><GuestStars>|Betty White|Stacey Scowley|</GuestStars><IMDB_ID>tt0795813</IMDB_ID><Language>en</Language><Overview>After reading an erotic novel, Peter gets the idea to write one himself. Carter gets sued for publishing Peter's book on tape and loses all his money, where he is forced to become a middle-class citizen. Meanwhile, Stewie tries to train for the Olympics.</Overview><ProductionCode>4ACX27</ProductionCode><Rating>7.2</Rating><RatingCount>838</RatingCount><SeasonNumber>4</SeasonNumber><Writer>|Patrick Meighan|</Writer><absolute_number>74</absolute_number><airsafter_season>0</airsafter_season><airsbefore_episode>0</airsbefore_episode><airsbefore_season>0</airsbefore_season><filename>episodes/75978/306264.jpg</filename><lastupdated>1629554566</lastupdated><seasonid>9515</seasonid><seriesid>75978</seriesid><thumb_added>2019-11-13 11:21:01</thumb_added><thumb_height>480</thumb_height><thumb_width>640</thumb_width></Episode>