<Banners><Banner><id>974872</id><BannerPath>graphical/270915-g.jpg</BannerPath><BannerType>series</BannerType><BannerType2>758x140</BannerType2><Language>en</Language><Season></Season><Colors></Colors><Rating>3.00</Rating><RatingCount>3</RatingCount><SeriesName>false</SeriesName><ThumbnailPath>graphical/270915-g_t.jpg</ThumbnailPath><VignettePath>graphical/270915-g_t.jpg</VignettePath></Banner><Banner><id>977367</id><BannerPath>graphical/270915-g2.jpg</BannerPath><BannerType>series</BannerType><BannerType2>758x140</BannerType2><Language>en</Language><Season></Season><Colors></Colors><Rating>2.00</Rating><RatingCount>2</RatingCount><SeriesName>false</SeriesName><ThumbnailPath>graphical/270915-g2_t.jpg</ThumbnailPath><VignettePath>graphical/270915-g2_t.jpg</VignettePath></Banner><Banner><id>978118</id><BannerPath>graphical/270915-g3.jpg</BannerPath><BannerType>series</BannerType><BannerType2>758x140</BannerType2><Language>en</Language><Season></Season><Colors></Colors><Rating>1.00</Rating><RatingCount>1</RatingCount><SeriesName>false</SeriesName><ThumbnailPath>graphical/270915-g3_t.jpg</ThumbnailPath><VignettePath>graphical/270915-g3_t.jpg</VignettePath></Banner><Banner><id>978128</id><BannerPath>graphical/270915-g4.jpg</BannerPath><BannerType>series</BannerType><BannerType2>758x140</BannerType2><Language>en</Language><Season></Season><Colors></Colors><Rating>2.00</Rating><RatingCount>2</RatingCount><SeriesName>false</SeriesName><ThumbnailPath>graphical/270915-g4_t.jpg</ThumbnailPath><VignettePath>graphical/270915-g4_t.jpg</VignettePath></Banner><Banner><id>978131</id><BannerPath>graphical/270915-g5.jpg</BannerPath><BannerType>series</BannerType><BannerType2>758x140</BannerType2><Language>en</Language><Season></Season><Colors></Colors><Rating>8.00</Rating><RatingCount>8</RatingCount><SeriesName>false</SeriesName><ThumbnailPath>graphical/270915-g5_t.jpg</ThumbnailPath><VignettePath>graphical/270915-g5_t.jpg</VignettePath></Banner><Banner><id>1056356</id><BannerPath>graphical/270915-g6.jpg</BannerPath><BannerType>series</BannerType><BannerType2>758x140</BannerType2><Language>en</Language><Season></Season><Colors></Colors><Rating>1.00</Rating><RatingCount>1</RatingCount><SeriesName>false</SeriesName><ThumbnailPath>graphical/270915-g6_t.jpg</ThumbnailPath><VignettePath>graphical/270915-g6_t.jpg</VignettePath></Banner><Banner><id>1056357</id><BannerPath>graphical/270915-g7.jpg</BannerPath><BannerType>series</BannerType><BannerType2>758x140</BannerType2><Language>en</Language><Season></Season><Colors></Colors><Rating>0.00</Rating><RatingCount>0</RatingCount><SeriesName>false</SeriesName><ThumbnailPath>graphical/270915-g7_t.jpg</ThumbnailPath><VignettePath>graphical/270915-g7_t.jpg</VignettePath></Banner><Banner><id>1131784</id><BannerPath>graphical/270915-g9.jpg</BannerPath><BannerType>series</BannerType><BannerType2>758x140</BannerType2><Language>en</Language><Season></Season><Colors></Colors><Rating>0.00</Rating><RatingCount>0</RatingCount><SeriesName>false</SeriesName><ThumbnailPath>graphical/270915-g9_t.jpg</ThumbnailPath><VignettePath>graphical/270915-g9_t.jpg</VignettePath></Banner><Banner><id>61118837</id><BannerPath>seasons/5d0010df30cdb.jpg</BannerPath><BannerType>season</BannerType><BannerType2>680x1000</BannerType2><Language>en</Language><Season>0</Season><Colors></Colors><Rating>0.00</Rating><RatingCount>0</RatingCount><SeriesName>false</SeriesName><ThumbnailPath>seasons/5d0010df30cdb_t.jpg</ThumbnailPath><VignettePath>seasons/5d0010df30cdb_t.jpg</VignettePath></Banner><Banner><id>61118872</id><BannerPath>seasons/5d73b1a315b9e.jpg</BannerPath><BannerType>season</BannerType><BannerType2>680x1000</BannerType2><Language>en</Language><Season>5</Season><Colors></Colors><Rating>0.00</Rating><RatingCount>0</RatingCount><SeriesName>false</SeriesName><ThumbnailPath>seasons/5d73b1a315b9e_t.jpg</ThumbnailPath><VignettePath>seasons/5d73b1a315b9e_t.jpg</VignettePath></Banner><Banner><id>61118873</id><BannerPath>seasons/5da32678387c8.jpg</BannerPath><BannerType>season</BannerType><BannerType2>680x1000</BannerType2><Language>en</Language><Season>5</Season><Colors></Colors><Rating>0.00</Rating><RatingCount>0</RatingCount><SeriesName>false</SeriesName><ThumbnailPath>seasons/5da32678387c8_t.jpg</ThumbnailPath><VignettePath>seasons/5da32678387c8_t.jpg</VignettePath></Banner><Banner><id>61118874</id><BannerPath>seasons/5d0010df30cdb.jpg</BannerPath><BannerType>season</BannerType><BannerType2>680x1000</BannerType2><Language>en</Language><Season>0</Season><Colors></Colors><Rating>0.00</Rating><RatingCount>0</RatingCount><SeriesName>false</SeriesName><ThumbnailPath>seasons/5d0010df30cdb_t.jpg</ThumbnailPath><VignettePath>seasons/5d0010df30cdb_t.jpg</VignettePath></Banner><Banner><id>61118884</id><BannerPath>seasons/5d73b1a315b9e.jpg</BannerPath><BannerType>season</BannerType><BannerType2>680x1000</BannerType2><Language>en</Language><Season>5</Season><Colors></Colors><Rating>0.00</Rating><RatingCount>0</RatingCount><SeriesName>false</SeriesName><ThumbnailPath>seasons/5d73b1a315b9e_t.jpg</ThumbnailPath><VignettePath>seasons/5d73b1a315b9e_t.jpg</VignettePath></Banner><Banner><id>61118885</id><BannerPath>seasons/5da32678387c8.jpg</BannerPath><BannerType>season</BannerType><BannerType2>680x1000</BannerType2><Language>en</Language><Season>5</Season><Colors></Colors><Rating>0.00</Rating><RatingCount>0</RatingCount><SeriesName>false</SeriesName><ThumbnailPath>seasons/5da32678387c8_t.jpg</ThumbnailPath><VignettePath>seasons/5da32678387c8_t.jpg</VignettePath></Banner><Banner><id>62965242</id><BannerPath>v4/season/523143/posters/61dd797e560f6.jpg</BannerPath><BannerType>season</BannerType><BannerType2>680x1000</BannerType2><Language>en</Language><Season>1</Season><Colors></Colors><Rating>0.00</Rating><RatingCount>0</RatingCount><SeriesName>false</SeriesName><ThumbnailPath>v4/season/523143/posters/61dd797e560f6_t.jpg</ThumbnailPath><VignettePath>v4/season/523143/posters/61dd797e560f6_t.jpg</VignettePath></Banner><Banner><id>62965245</id><BannerPath>v4/season/597799/posters/61dd7b0ff3cd5.jpg</BannerPath><BannerType>season</BannerType><BannerType2>680x1000</BannerType2><Language>en</Language><Season>2</Season><Colors></Colors><Rating>0.00</Rating><RatingCount>0</RatingCount><SeriesName>false</SeriesName><ThumbnailPath>v4/season/597799/posters/61dd7b0ff3cd5_t.jpg</ThumbnailPath><VignettePath>v4/season/597799/posters/61dd7b0ff3cd5_t.jpg</VignettePath></Banner><Banner><id>62965246</id><BannerPath>v4/season/654172/posters/61dd7ba72c3eb.jpg</BannerPath><BannerType>season</BannerType><BannerType2>680x1000</BannerType2><Language>en</Language><Season>3</Season><Colors></Colors><Rating>0.00</Rating><RatingCount>0</RatingCount><SeriesName>false</SeriesName><ThumbnailPath>v4/season/654172/posters/61dd7ba72c3eb_t.jpg</ThumbnailPath><VignettePath>v4/season/654172/posters/61dd7ba72c3eb_t.jpg</VignettePath></Banner><Banner><id>62965250</id><BannerPath>v4/season/718740/posters/61dd7e10169e8.jpg</BannerPath><BannerType>season</BannerType><BannerType2>680x1000</BannerType2><Language>en</Language><Season>4</Season><Colors></Colors><Rating>0.00</Rating><RatingCount>0</RatingCount><SeriesName>false</SeriesName><ThumbnailPath>v4/season/718740/posters/61dd7e10169e8_t.jpg</ThumbnailPath><VignettePath>v4/season/718740/posters/61dd7e10169e8_t.jpg</VignettePath></Banner><Banner><id>63012033</id><BannerPath>v4/season/1978761/posters/621f260d29e6d.jpg</BannerPath><BannerType>season</BannerType><BannerType2>680x1000</BannerType2><Language>en</Language><Season>6</Season><Colors></Colors><Rating>0.00</Rating><RatingCount>0</RatingCount><SeriesName>false</SeriesName><ThumbnailPath>v4/season/1978761/posters/621f260d29e6d_t.jpg</ThumbnailPath><VignettePath>v4/season/1978761/posters/621f260d29e6d_t.jpg</VignettePath></Banner><Banner><id>63050300</id><BannerPath>v4/season/1978761/posters/6254146baf679.jpg</BannerPath><BannerType>season</BannerType><BannerType2>680x1000</BannerType2><Language>en</Language><Season>6</Season><Colors></Colors><Rating>0.00</Rating><RatingCount>0</RatingCount><SeriesName>false</SeriesName><ThumbnailPath>v4/season/1978761/posters/6254146baf679_t.jpg</ThumbnailPath><VignettePath>v4/season/1978761/posters/6254146baf679_t.jpg</VignettePath></Banner><Banner><id>1008033</id><BannerPath>fanart/original/270915-8.jpg</BannerPath><BannerType>fanart</BannerType><BannerType2>1920x1080</BannerType2><Language>en</Language><Season></Season><Colors></Colors><Rating>10.00</Rating><RatingCount>10</RatingCount><SeriesName>false</SeriesName><ThumbnailPath>fanart/original/270915-8_t.jpg</ThumbnailPath><VignettePath>fanart/original/270915-8_t.jpg</VignettePath></Banner><Banner><id>1046595</id><BannerPath>fanart/original/270915-10.jpg</BannerPath><BannerType>fanart</BannerType><BannerType2>1920x1080</BannerType2><Language>en</Language><Season></Season><Colors></Colors><Rating>10.00</Rating><RatingCount>10</RatingCount><SeriesName>false</SeriesName><ThumbnailPath>fanart/original/270915-10_t.jpg</ThumbnailPath><VignettePath>fanart/original/270915-10_t.jpg</VignettePath></Banner><Banner><id>1072113</id><BannerPath>fanart/original/270915-11.jpg</BannerPath><BannerType>fanart</BannerType><BannerType2>1920x1080</BannerType2><Language>en</Language><Season></Season><Colors></Colors><Rating>3.00</Rating><RatingCount>3</RatingCount><SeriesName>false</SeriesName><ThumbnailPath>fanart/original/270915-11_t.jpg</ThumbnailPath><VignettePath>fanart/original/270915-11_t.jpg</VignettePath></Banner><Banner><id>1072114</id><BannerPath>fanart/original/270915-12.jpg</BannerPath><BannerType>fanart</BannerType><BannerType2>1920x1080</BannerType2><Language>en</Language><Season></Season><Colors></Colors><Rating>3.00</Rating><RatingCount>3</RatingCount><SeriesName>false</SeriesName><ThumbnailPath>fanart/original/270915-12_t.jpg</ThumbnailPath><VignettePath>fanart/original/270915-12_t.jpg</VignettePath></Banner><Banner><id>1106175</id><BannerPath>fanart/original/270915-14.jpg</BannerPath><BannerType>fanart</BannerType><BannerType2>1920x1080</BannerType2><Language>en</Language><Season></Season><Colors></Colors><Rating>1.00</Rating><RatingCount>1</RatingCount><SeriesName>false</SeriesName><ThumbnailPath>fanart/original/270915-14_t.jpg</ThumbnailPath><VignettePath>fanart/original/270915-14_t.jpg</VignettePath></Banner><Banner><id>1243904</id><BannerPath>fanart/original/270915-4.jpg</BannerPath><BannerType>fanart</BannerType><BannerType2>1920x1080</BannerType2><Language>en</Language><Season></Season><Colors></Colors><Rating>3.00</Rating><RatingCount>3</RatingCount><SeriesName>false</SeriesName><ThumbnailPath>fanart/original/270915-4_t.jpg</ThumbnailPath><VignettePath>fanart/original/270915-4_t.jpg</VignettePath></Banner><Banner><id>1243905</id><BannerPath>fanart/original/270915-16.jpg</BannerPath><BannerType>fanart</BannerType><BannerType2>1920x1080</BannerType2><Language>en</Language><Season></Season><Colors></Colors><Rating>0.00</Rating><RatingCount>0</RatingCount><SeriesName>false</SeriesName><ThumbnailPath>fanart/original/270915-16_t.jpg</ThumbnailPath><VignettePath>fanart/original/270915-16_t.jpg</VignettePath></Banner><Banner><id>1252945</id><BannerPath>fanart/original/270915-17.jpg</BannerPath><BannerType>fanart</BannerType><BannerType2>1920x1080</BannerType2><Language>en</Language><Season></Season><Colors></Colors><Rating>0.00</Rating><RatingCount>0</RatingCount><SeriesName>false</SeriesName><ThumbnailPath>fanart/original/270915-17_t.jpg</ThumbnailPath><VignettePath>fanart/original/270915-17_t.jpg</VignettePath></Banner><Banner><id>1379614</id><BannerPath>fanart/original/5d4b68b8c7987.jpg</BannerPath><BannerType>fanart</BannerType><BannerType2>1920x1080</BannerType2><Language>en</Language><Season></Season><Colors></Colors><Rating>0.00</Rating><RatingCount>0</RatingCount><SeriesName>false</SeriesName><ThumbnailPath>fanart/original/5d4b68b8c7987_t.jpg</ThumbnailPath><VignettePath>fanart/original/5d4b68b8c7987_t.jpg</VignettePath></Banner><Banner><id>1379615</id><BannerPath>fanart/original/5d4b69320d985.jpg</BannerPath><BannerType>fanart</BannerType><BannerType2>1920x1080</BannerType2><Language>en</Language><Season></Season><Colors></Colors><Rating>1.00</Rating><RatingCount>1</RatingCount><SeriesName>false</SeriesName><ThumbnailPath>fanart/original/5d4b69320d985_t.jpg</ThumbnailPath><VignettePath>fanart/original/5d4b69320d985_t.jpg</VignettePath></Banner><Banner><id>1398198</id><BannerPath>fanart/original/5dc015030337d.jpg</BannerPath><BannerType>fanart</BannerType><BannerType2>1920x1080</BannerType2><Language>en</Language><Season></Season><Colors></Colors><Rating>0.00</Rating><RatingCount>0</RatingCount><SeriesName>false</SeriesName><ThumbnailPath>fanart/original/5dc015030337d_t.jpg</ThumbnailPath><VignettePath>fanart/original/5dc015030337d_t.jpg</VignettePath></Banner><Banner><id>62392147</id><BannerPath>series/270915/backgrounds/5fad42e0cdb43.jpg</BannerPath><BannerType>fanart</BannerType><BannerType2>1920x1080</BannerType2><Language></Language><Season></Season><Colors></Colors><Rating>0.00</Rating><RatingCount>0</RatingCount><SeriesName>false</SeriesName><ThumbnailPath>series/270915/backgrounds/5fad42e0cdb43_t.jpg</ThumbnailPath><VignettePath>series/270915/backgrounds/5fad42e0cdb43_t.jpg</VignettePath></Banner><Banner><id>63011496</id><BannerPath>v4/series/270915/backgrounds/621e607fe08c1.jpg</BannerPath><BannerType>fanart</BannerType><BannerType2>1920x1080</BannerType2><Language>en</Language><Season></Season><Colors></Colors><Rating>0.00</Rating><RatingCount>0</RatingCount><SeriesName>false</SeriesName><ThumbnailPath>v4/series/270915/backgrounds/621e607fe08c1_t.jpg</ThumbnailPath><VignettePath>v4/series/270915/backgrounds/621e607fe08c1_t.jpg</VignettePath></Banner><Banner><id>1045988</id><BannerPath>posters/270915-6.jpg</BannerPath><BannerType>poster</BannerType><BannerType2>680x1000</BannerType2><Language>en</Language><Season></Season><Colors></Colors><Rating>2.00</Rating><RatingCount>2</RatingCount><SeriesName>false</SeriesName><ThumbnailPath>posters/270915-6_t.jpg</ThumbnailPath><VignettePath>posters/270915-6_t.jpg</VignettePath></Banner><Banner><id>1046594</id><BannerPath>posters/270915-7.jpg</BannerPath><BannerType>poster</BannerType><BannerType2>680x1000</BannerType2><Language>en</Language><Season></Season><Colors></Colors><Rating>11.00</Rating><RatingCount>11</RatingCount><SeriesName>false</SeriesName><ThumbnailPath>posters/270915-7_t.jpg</ThumbnailPath><VignettePath>posters/270915-7_t.jpg</VignettePath></Banner><Banner><id>1069953</id><BannerPath>posters/270915-8.jpg</BannerPath><BannerType>poster</BannerType><BannerType2>680x1000</BannerType2><Language>en</Language><Season></Season><Colors></Colors><Rating>0.00</Rating><RatingCount>0</RatingCount><SeriesName>false</SeriesName><ThumbnailPath>posters/270915-8_t.jpg</ThumbnailPath><VignettePath>posters/270915-8_t.jpg</VignettePath></Banner><Banner><id>1072110</id><BannerPath>posters/270915-10.jpg</BannerPath><BannerType>poster</BannerType><BannerType2>680x1000</BannerType2><Language>en</Language><Season></Season><Colors></Colors><Rating>9.00</Rating><RatingCount>9</RatingCount><SeriesName>false</SeriesName><ThumbnailPath>posters/270915-10_t.jpg</ThumbnailPath><VignettePath>posters/270915-10_t.jpg</VignettePath></Banner><Banner><id>1139280</id><BannerPath>posters/270915-12.jpg</BannerPath><BannerType>poster</BannerType><BannerType2>680x1000</BannerType2><Language>en</Language><Season></Season><Colors></Colors><Rating>4.00</Rating><RatingCount>4</RatingCount><SeriesName>false</SeriesName><ThumbnailPath>posters/270915-12_t.jpg</ThumbnailPath><VignettePath>posters/270915-12_t.jpg</VignettePath></Banner><Banner><id>1142581</id><BannerPath>posters/270915-13.jpg</BannerPath><BannerType>poster</BannerType><BannerType2>680x1000</BannerType2><Language>en</Language><Season></Season><Colors></Colors><Rating>13.00</Rating><RatingCount>13</RatingCount><SeriesName>false</SeriesName><ThumbnailPath>posters/270915-13_t.jpg</ThumbnailPath><VignettePath>posters/270915-13_t.jpg</VignettePath></Banner><Banner><id>1142843</id><BannerPath>posters/270915-14.jpg</BannerPath><BannerType>poster</BannerType><BannerType2>680x1000</BannerType2><Language>en</Language><Season></Season><Colors></Colors><Rating>2.00</Rating><RatingCount>2</RatingCount><SeriesName>false</SeriesName><ThumbnailPath>posters/270915-14_t.jpg</ThumbnailPath><VignettePath>posters/270915-14_t.jpg</VignettePath></Banner><Banner><id>1185496</id><BannerPath>posters/270915-17.jpg</BannerPath><BannerType>poster</BannerType><BannerType2>680x1000</BannerType2><Language>en</Language><Season></Season><Colors></Colors><Rating>0.00</Rating><RatingCount>0</RatingCount><SeriesName>false</SeriesName><ThumbnailPath>posters/270915-17_t.jpg</ThumbnailPath><VignettePath>posters/270915-17_t.jpg</VignettePath></Banner><Banner><id>1185815</id><BannerPath>posters/270915-18.jpg</BannerPath><BannerType>poster</BannerType><BannerType2>680x1000</BannerType2><Language>en</Language><Season></Season><Colors></Colors><Rating>0.00</Rating><RatingCount>0</RatingCount><SeriesName>false</SeriesName><ThumbnailPath>posters/270915-18_t.jpg</ThumbnailPath><VignettePath>posters/270915-18_t.jpg</VignettePath></Banner><Banner><id>1187814</id><BannerPath>posters/270915-19.jpg</BannerPath><BannerType>poster</BannerType><BannerType2>680x1000</BannerType2><Language>en</Language><Season></Season><Colors></Colors><Rating>0.00</Rating><RatingCount>0</RatingCount><SeriesName>false</SeriesName><ThumbnailPath>posters/270915-19_t.jpg</ThumbnailPath><VignettePath>posters/270915-19_t.jpg</VignettePath></Banner><Banner><id>1216141</id><BannerPath>posters/270915-15.jpg</BannerPath><BannerType>poster</BannerType><BannerType2>680x1000</BannerType2><Language>en</Language><Season></Season><Colors></Colors><Rating>1.00</Rating><RatingCount>1</RatingCount><SeriesName>false</SeriesName><ThumbnailPath>posters/270915-15_t.jpg</ThumbnailPath><VignettePath>posters/270915-15_t.jpg</VignettePath></Banner><Banner><id>1216142</id><BannerPath>posters/270915-16.jpg</BannerPath><BannerType>poster</BannerType><BannerType2>680x1000</BannerType2><Language>en</Language><Season></Season><Colors></Colors><Rating>0.00</Rating><RatingCount>0</RatingCount><SeriesName>false</SeriesName><ThumbnailPath>posters/270915-16_t.jpg</ThumbnailPath><VignettePath>posters/270915-16_t.jpg</VignettePath></Banner><Banner><id>1231796</id><BannerPath>posters/270915-20.jpg</BannerPath><BannerType>poster</BannerType><BannerType2>680x1000</BannerType2><Language>en</Language><Season></Season><Colors></Colors><Rating>12.00</Rating><RatingCount>12</RatingCount><SeriesName>false</SeriesName><ThumbnailPath>posters/270915-20_t.jpg</ThumbnailPath><VignettePath>posters/270915-20_t.jpg</VignettePath></Banner><Banner><id>1253804</id><BannerPath>posters/270915-21.jpg</BannerPath><BannerType>poster</BannerType><BannerType2>680x1000</BannerType2><Language>en</Language><Season></Season><Colors></Colors><Rating>13.00</Rating><RatingCount>13</RatingCount><SeriesName>false</SeriesName><ThumbnailPath>posters/270915-21_t.jpg</ThumbnailPath><VignettePath>posters/270915-21_t.jpg</VignettePath></Banner><Banner><id>1318094</id><BannerPath>posters/5be026f3548e9.jpg</BannerPath><BannerType>poster</BannerType><BannerType2>680x1000</BannerType2><Language>en</Language><Season></Season><Colors></Colors><Rating>0.00</Rating><RatingCount>0</RatingCount><SeriesName>false</SeriesName><ThumbnailPath>posters/5be026f3548e9_t.jpg</ThumbnailPath><VignettePath>posters/5be026f3548e9_t.jpg</VignettePath></Banner><Banner><id>1320500</id><BannerPath>posters/5bf153d4273e9.jpg</BannerPath><BannerType>poster</BannerType><BannerType2>680x1000</BannerType2><Language>en</Language><Season></Season><Colors></Colors><Rating>0.00</Rating><RatingCount>0</RatingCount><SeriesName>false</SeriesName><ThumbnailPath>posters/5bf153d4273e9_t.jpg</ThumbnailPath><VignettePath>posters/5bf153d4273e9_t.jpg</VignettePath></Banner><Banner><id>1321761</id><BannerPath>posters/5bfada9f00205.jpg</BannerPath><BannerType>poster</BannerType><BannerType2>680x1000</BannerType2><Language>en</Language><Season></Season><Colors></Colors><Rating>14.00</Rating><RatingCount>14</RatingCount><SeriesName>false</SeriesName><ThumbnailPath>posters/5bfada9f00205_t.jpg</ThumbnailPath><VignettePath>posters/5bfada9f00205_t.jpg</VignettePath></Banner><Banner><id>1323286</id><BannerPath>posters/5c07014fea7cb.jpg</BannerPath><BannerType>poster</BannerType><BannerType2>680x1000</BannerType2><Language>en</Language><Season></Season><Colors></Colors><Rating>0.00</Rating><RatingCount>0</RatingCount><SeriesName>false</SeriesName><ThumbnailPath>posters/5c07014fea7cb_t.jpg</ThumbnailPath><VignettePath>posters/5c07014fea7cb_t.jpg</VignettePath></Banner><Banner><id>1356823</id><BannerPath>posters/5cbe42c55ca40.jpg</BannerPath><BannerType>poster</BannerType><BannerType2>680x1000</BannerType2><Language>en</Language><Season></Season><Colors></Colors><Rating>0.00</Rating><RatingCount>0</RatingCount><SeriesName>false</SeriesName><ThumbnailPath>posters/5cbe42c55ca40_t.jpg</ThumbnailPath><VignettePath>posters/5cbe42c55ca40_t.jpg</VignettePath></Banner><Banner><id>1376438</id><BannerPath>posters/5d32fbc83e33f.jpg</BannerPath><BannerType>poster</BannerType><BannerType2>680x1000</BannerType2><Language>en</Language><Season></Season><Colors></Colors><Rating>0.00</Rating><RatingCount>0</RatingCount><SeriesName>false</SeriesName><ThumbnailPath>posters/5d32fbc83e33f_t.jpg</ThumbnailPath><VignettePath>posters/5d32fbc83e33f_t.jpg</VignettePath></Banner><Banner><id>62050838</id><BannerPath>series/270915/posters/62050838.jpg</BannerPath><BannerType>poster</BannerType><BannerType2>680x1000</BannerType2><Language>en</Language><Season></Season><Colors></Colors><Rating>0.00</Rating><RatingCount>0</RatingCount><SeriesName>false</SeriesName><ThumbnailPath>series/270915/posters/62050838_t.jpg</ThumbnailPath><VignettePath>series/270915/posters/62050838_t.jpg</VignettePath></Banner><Banner><id>62080099</id><BannerPath>series/270915/posters/62080099.jpg</BannerPath><BannerType>poster</BannerType><BannerType2>680x1000</BannerType2><Language>en</Language><Season></Season><Colors></Colors><Rating>8.00</Rating><RatingCount>8</RatingCount><SeriesName>false</SeriesName><ThumbnailPath>series/270915/posters/62080099_t.jpg</ThumbnailPath><VignettePath>series/270915/posters/62080099_t.jpg</VignettePath></Banner><Banner><id>62521608</id><BannerPath>series/270915/posters/60424b93bccf9.jpg</BannerPath><BannerType>poster</BannerType><BannerType2>680x1000</BannerType2><Language>en</Language><Season></Season><Colors></Colors><Rating>3.00</Rating><RatingCount>3</RatingCount><SeriesName>false</SeriesName><ThumbnailPath>series/270915/posters/60424b93bccf9_t.jpg</ThumbnailPath><VignettePath>series/270915/posters/60424b93bccf9_t.jpg</VignettePath></Banner><Banner><id>63011493</id><BannerPath>v4/series/270915/posters/621e60438d38e.jpg</BannerPath><BannerType>poster</BannerType><BannerType2>680x1000</BannerType2><Language>en</Language><Season></Season><Colors></Colors><Rating>0.00</Rating><RatingCount>0</RatingCount><SeriesName>false</SeriesName><ThumbnailPath>v4/series/270915/posters/621e60438d38e_t.jpg</ThumbnailPath><VignettePath>v4/series/270915/posters/621e60438d38e_t.jpg</VignettePath></Banner></Banners>