<?xml version="1.0" encoding="utf-8"?><Episode><id>9003220</id><Combined_episodenumber>11</Combined_episodenumber><Combined_season>9</Combined_season><DVD_chapter>0</DVD_chapter><DVD_discid></DVD_discid><DVD_episodenumber>11</DVD_episodenumber><DVD_season>9</DVD_season><Director>|Adam T. Weisinger|</Director><EpImgFlag></EpImgFlag><EpisodeName>The Conglomerate</EpisodeName><EpisodeNumber>11</EpisodeNumber><FirstAired>2022-03-04</FirstAired><GuestStars></GuestStars><IMDB_ID>tt18285230</IMDB_ID><Language>en</Language><Overview>An investigation into the Conglomerate, a group of former government-sponsored assassins, becomes complicated when the task force learns one of their own may have ties to the group. Red digs deeper into the events leading up to Liz's death.</Overview><ProductionCode>911</ProductionCode><Rating>0</Rating><RatingCount>0</RatingCount><SeasonNumber>9</SeasonNumber><Writer>|Aiah Samba|</Writer><absolute_number>185</absolute_number><airsafter_season>0</airsafter_season><airsbefore_episode>0</airsbefore_episode><airsbefore_season>0</airsbefore_season><filename>v4/episode/9003220/screencap/62230449ec905.jpg</filename><lastupdated>1653748498</lastupdated><seasonid>1943454</seasonid><seriesid>266189</seriesid><thumb_added>2022-03-05 06:33:46</thumb_added><thumb_height>360</thumb_height><thumb_width>640</thumb_width></Episode>