<?xml version="1.0" encoding="utf-8"?><Episode><id>5041679</id><Combined_episodenumber>10</Combined_episodenumber><Combined_season>2</Combined_season><DVD_chapter>0</DVD_chapter><DVD_discid></DVD_discid><DVD_episodenumber>10</DVD_episodenumber><DVD_season>2</DVD_season><Director>|Michael Watkins|</Director><EpImgFlag></EpImgFlag><EpisodeName>Luther Braxton: Conclusion</EpisodeName><EpisodeNumber>10</EpisodeNumber><FirstAired>2015-02-05</FirstAired><GuestStars>|David Strathairn|Janel Moloney|Ron Perlman|</GuestStars><IMDB_ID>tt4283600</IMDB_ID><Language>en</Language><Overview>As chaos ensues at the Factory, leaving the fate of Red and the task force unknown, Cooper struggles to rescue his team from the detention facility. It’s a race against time to prevent Luther Braxton attaining confidential information.</Overview><ProductionCode></ProductionCode><Rating>7.6</Rating><RatingCount>1535</RatingCount><SeasonNumber>2</SeasonNumber><Writer>|Jim Campolongo|Kristen Reidel|Mike Ostrowski|Vincent Angell|</Writer><absolute_number>32</absolute_number><airsafter_season>0</airsafter_season><airsbefore_episode>0</airsbefore_episode><airsbefore_season>0</airsbefore_season><filename>episodes/266189/5041679.jpg</filename><lastupdated>1648147407</lastupdated><seasonid>587363</seasonid><seriesid>266189</seriesid><thumb_added>2019-11-13 12:06:45</thumb_added><thumb_height>360</thumb_height><thumb_width>640</thumb_width></Episode>