<?xml version="1.0" encoding="utf-8"?><Episode><id>5471863</id><Combined_episodenumber>15</Combined_episodenumber><Combined_season>3</Combined_season><DVD_chapter>0</DVD_chapter><DVD_discid></DVD_discid><DVD_episodenumber>15</DVD_episodenumber><DVD_season>3</DVD_season><Director>|Anton Cropper|</Director><EpImgFlag></EpImgFlag><EpisodeName>Drexel</EpisodeName><EpisodeNumber>15</EpisodeNumber><FirstAired>2016-02-18</FirstAired><GuestStars></GuestStars><IMDB_ID>tt5182076</IMDB_ID><Language>en</Language><Overview>After the founder of a successful internet start-up is found dead, Red recognizes the crime scene as the work of a notorious killer. Liz and the task force work with Red to track the murderer through a dangerous underground news source. Meanwhile, Tom faces a life threatening situation, while Liz considers options for her baby.</Overview><ProductionCode></ProductionCode><Rating>7.6</Rating><RatingCount>670</RatingCount><SeasonNumber>3</SeasonNumber><Writer>|Dave Metzger|</Writer><absolute_number>59</absolute_number><airsafter_season>0</airsafter_season><airsbefore_episode>0</airsbefore_episode><airsbefore_season>0</airsbefore_season><filename>episodes/266189/5471863.jpg</filename><lastupdated>1648148048</lastupdated><seasonid>626832</seasonid><seriesid>266189</seriesid><thumb_added>2019-11-13 12:06:45</thumb_added><thumb_height>360</thumb_height><thumb_width>640</thumb_width></Episode>