<?xml version="1.0" encoding="utf-8"?><Episode><id>179591</id><Combined_episodenumber>5</Combined_episodenumber><Combined_season>4</Combined_season><DVD_chapter>0</DVD_chapter><DVD_discid></DVD_discid><DVD_episodenumber>5</DVD_episodenumber><DVD_season>4</DVD_season><Director>|Eric Stough|</Director><EpImgFlag></EpImgFlag><EpisodeName>Cartman Joins NAMBLA</EpisodeName><EpisodeNumber>5</EpisodeNumber><FirstAired>2000-06-21</FirstAired><GuestStars></GuestStars><IMDB_ID>tt0769424</IMDB_ID><Language>en</Language><Overview>Cartman decides to seek the friendship of older men. Using the Internet, he makes a connection with men who love to hang out with little boys. An organization called NAMBLA (North American Man Boy Love Association) holds a meeting in South Park and Cartman becomes their poster child. The boys learn how much an adult can really love a child.</Overview><ProductionCode>406</ProductionCode><Rating>7.5</Rating><RatingCount>924</RatingCount><SeasonNumber>4</SeasonNumber><Writer>|Trey Parker|</Writer><absolute_number>53</absolute_number><airsafter_season>0</airsafter_season><airsbefore_episode>0</airsbefore_episode><airsbefore_season>0</airsbefore_season><filename>episodes/75897/179591.jpg</filename><lastupdated>1610885612</lastupdated><seasonid>9418</seasonid><seriesid>75897</seriesid><thumb_added>2019-11-13 10:35:15</thumb_added><thumb_height>480</thumb_height><thumb_width>640</thumb_width></Episode>