<?xml version="1.0" encoding="utf-8"?><Episode><id>179663</id><Combined_episodenumber>12</Combined_episodenumber><Combined_season>8</Combined_season><DVD_chapter>0</DVD_chapter><DVD_discid></DVD_discid><DVD_episodenumber>12</DVD_episodenumber><DVD_season>8</DVD_season><Director>|Trey Parker|</Director><EpImgFlag></EpImgFlag><EpisodeName>Stupid Spoiled Whore Video Playset</EpisodeName><EpisodeNumber>12</EpisodeNumber><FirstAired>2004-12-01</FirstAired><GuestStars>|Jessie Thomas|Paula Holmberg|</GuestStars><IMDB_ID>tt0705965</IMDB_ID><Language>en</Language><Overview>All the fourth grade girls idolize a rich, famous and spoiled socialite. They even have her brand new toy set that comes complete with video camera, night vision filter, play money and losable cell phone. In an effort to impress their idol, the girls pursue the boys to make their own videos.</Overview><ProductionCode>812</ProductionCode><Rating>7.5</Rating><RatingCount>839</RatingCount><SeasonNumber>8</SeasonNumber><Writer>|Trey Parker|</Writer><absolute_number>123</absolute_number><airsafter_season>0</airsafter_season><airsbefore_episode>0</airsbefore_episode><airsbefore_season>0</airsbefore_season><filename>episodes/75897/179663.jpg</filename><lastupdated>1602384344</lastupdated><seasonid>9422</seasonid><seriesid>75897</seriesid><thumb_added>2019-11-13 10:35:15</thumb_added><thumb_height>480</thumb_height><thumb_width>640</thumb_width></Episode>