<?xml version="1.0" encoding="utf-8"?><Episode><id>6092247</id><Combined_episodenumber>2</Combined_episodenumber><Combined_season>21</Combined_season><DVD_chapter>0</DVD_chapter><DVD_discid></DVD_discid><DVD_episodenumber>2</DVD_episodenumber><DVD_season>21</DVD_season><Director>|Trey Parker|</Director><EpImgFlag></EpImgFlag><EpisodeName>Put It Down</EpisodeName><EpisodeNumber>2</EpisodeNumber><FirstAired>2017-09-20</FirstAired><GuestStars></GuestStars><IMDB_ID>tt7181718</IMDB_ID><Language>en</Language><Overview>When Tweek is caught in the middle of a petty conflict, it drives his relationship with Craig to the brink.</Overview><ProductionCode>2102</ProductionCode><Rating>7.8</Rating><RatingCount>172</RatingCount><SeasonNumber>21</SeasonNumber><Writer>|Trey Parker|</Writer><absolute_number>279</absolute_number><airsafter_season>0</airsafter_season><airsbefore_episode>0</airsbefore_episode><airsbefore_season>0</airsbefore_season><filename>episodes/75897/6092247.jpg</filename><lastupdated>1611606723</lastupdated><seasonid>712290</seasonid><seriesid>75897</seriesid><thumb_added>2019-11-13 10:35:15</thumb_added><thumb_height>360</thumb_height><thumb_width>640</thumb_width></Episode>