<?xml version="1.0" encoding="utf-8"?><Episode><id>131224</id><Combined_episodenumber>7</Combined_episodenumber><Combined_season>4</Combined_season><DVD_chapter>0</DVD_chapter><DVD_discid></DVD_discid><DVD_episodenumber>17</DVD_episodenumber><DVD_season>3</DVD_season><Director>|Mark Ervin|</Director><EpImgFlag></EpImgFlag><EpisodeName>A Pharaoh to Remember</EpisodeName><EpisodeNumber>7</EpisodeNumber><FirstAired>2002-03-10</FirstAired><GuestStars></GuestStars><IMDB_ID>tt0756878</IMDB_ID><Language>en</Language><Overview>Bender fears that nobody will remember him after he dies, and sees his chance for immortality when the crew is enslaved on the planet Osiris 4. Posing as the planet's new pharaoh, Bender orders a humongous statue built in his honor, and quickly goes mad with power.</Overview><ProductionCode>3ACV17</ProductionCode><Rating>7.4</Rating><RatingCount>1650</RatingCount><SeasonNumber>4</SeasonNumber><Writer>|Ron Weiner|</Writer><absolute_number>49</absolute_number><airsafter_season>0</airsafter_season><airsbefore_episode>0</airsbefore_episode><airsbefore_season>0</airsbefore_season><filename>episodes/73871/131224.jpg</filename><lastupdated>1630895156</lastupdated><seasonid>6591</seasonid><seriesid>73871</seriesid><thumb_added>2019-11-13 12:03:12</thumb_added><thumb_height>480</thumb_height><thumb_width>640</thumb_width></Episode>